happy/__init__.py
happy/happy.py
testangle-1.0.4.dist-info/LICENSE
testangle-1.0.4.dist-info/METADATA
testangle-1.0.4.dist-info/WHEEL
testangle-1.0.4.dist-info/top_level.txt
testangle-1.0.4.dist-info/RECORD
