Metadata-Version: 2.1
Name: testangle
Version: 1.0.4
Summary: 撰写一个简单的列子
Home-page: https://github.com/1abner1/tianshou
Author: xww
Author-email: axiaowwa@163.com
License: UNKNOWN
Platform: UNKNOWN
Classifier: Programming Language :: Python :: 3.8
Classifier: License :: OSI Approved :: MIT License
Classifier: Operating System :: OS Independent
License-File: LICENSE
Requires-Dist: pillow
Requires-Dist: tensorboard
Requires-Dist: torch
